twitterhistory/__init__.py
twitterhistory/__main__.py
twitterhistory/apikeymanager.py
twitterhistory/basictwitterhistorydownloader.py
twitterhistory/cache.py
twitterhistory/cacheupdaterthread.py
twitterhistory/config.py
twitterhistory/exceptions.py
twitterhistory/fancytwitterhistorydownloader.py
twitterhistory/integer_hash.py
twitterhistory/sigtermreceivedexception.py
twitterhistory/timeoutlock.py
twitterhistory/timespan.py
twitterhistory/twitterhistorydownloader.py
twitterhistory/database/__init__.py
twitterhistory/database/apiresponsesaver.py
twitterhistory/database/baseitemsaver.py
twitterhistory/database/databaseschemaupdater.py
twitterhistory/database/engine.py
twitterhistory/database/errorssaver.py
twitterhistory/database/includessaver.py
twitterhistory/database/likessaver.py
twitterhistory/database/mediaitemsaver.py
twitterhistory/database/placesaver.py
twitterhistory/database/tweetsaver.py
twitterhistory/database/usersaver.py
twitterhistory/database/models/__init__.py
twitterhistory/database/models/base.py
twitterhistory/database/models/conversation.py
twitterhistory/database/models/hashtag.py
twitterhistory/database/models/language.py
twitterhistory/database/models/mediaitem.py
twitterhistory/database/models/place.py
twitterhistory/database/models/searchterm.py
twitterhistory/database/models/tweet.py
twitterhistory/database/models/url.py
twitterhistory/database/models/user.py
twitterhistory/downloaders/__init__.py
twitterhistory/downloaders/basedownloader.py
twitterhistory/downloaders/basedownloaderthread.py
twitterhistory/downloaders/baseworkerthread.py
twitterhistory/downloaders/gettweetssearchalldownloader.py
twitterhistory/downloaders/gettweetssearchalldownloaderthread.py
twitterhistory/downloaders/incompletedatafinderthread.py
twitterhistory/downloaders/incompletedataupdater.py
twitterhistory/downloaders/incompletedataupdaterthread.py
twitterhistory/downloaders/incompletetweetfinderthread.py
twitterhistory/downloaders/incompletetweetupdater.py
twitterhistory-0.3.6.dist-info/LICENSE
twitterhistory-0.3.6.dist-info/METADATA
twitterhistory-0.3.6.dist-info/WHEEL
twitterhistory-0.3.6.dist-info/top_level.txt
twitterhistory-0.3.6.dist-info/RECORD
