Metadata-Version: 2.1
Name: twitterhistory
Version: 0.3.6
Summary: Download posts and user metadata from the microblogging service Twitter
Home-page: https://gitlab.com/christoph.fink/twitterhistory/
Author: Christoph Fink
Author-email: christoph.fink@helsinki.fi
License: GPLv3
Platform: UNKNOWN
Classifier: Programming Language :: Python :: 3
Classifier: License :: OSI Approved :: GNU General Public License v3 (GPLv3)
Classifier: Operating System :: OS Independent
License-File: LICENSE
Requires-Dist: blessed
Requires-Dist: dateparser
Requires-Dist: GeoAlchemy2
Requires-Dist: PyYAML
Requires-Dist: psycopg2
Requires-Dist: requests
Requires-Dist: shapely
Requires-Dist: SQLAlchemy (>=1.4.0)
